LICENSE
MANIFEST.in
README.md
README.rst
setup.py
randdate/__init__.py
randdate/randdate.py
randdate.egg-info/PKG-INFO
randdate.egg-info/SOURCES.txt
randdate.egg-info/dependency_links.txt
randdate.egg-info/top_level.txt
randdate.egg-info/zip-safe