Metadata-Version: 2.1
Name: randdate
Version: 0.1.1
Summary: Generate a list of random dates or resp. datetime objects
Home-page: http://github.com/kmedian/randdate
Author: Ulf Hamster
Author-email: 554c46@gmail.com
License: Apache License 2.0
Platform: UNKNOWN
Requires-Python: >=3.6
